{"1143":"BM-","1144":"BM-","1371":"BS-FP","1370":"BS-NS","1385":"BS-NP","1380":"BS-RS","1365":"BS-MH","1382":"BS-GH","1363":"BS-FP","1381":"BS-SP","1707":"BS-LI","1715":"BS-SR","1362":"BS-GT","1386":"BS-CI","1383":"BS-HI","1706":"BS-LI","1697":"BS-IN","1364":"BS-FP","1708":"BS-EX","1704":"BS-RI","1714":"BS-CI","1368":"BS-BI","1477":"BS-KB","1696":"BS-AC","1384":"BS-EX","1698":"BS-AC","1369":"US-FL","1379":"US-FL","1705":"CU-11","1465":"CU-05","1466":"BS-BI","1799":"CR-A","1798":"CR-G","1766":"CR-H","1800":"CR-G","1752":"CR-SJ","1750":"CR-P","1754":"CR-P","1753":"CR-P","1802":"CR-A","1801":"CR-P","1767":"CR-L","1771":"CR-P","1751":"PA-4","1796":"CR-P","1797":"CR-P","1770":"CR-P","1772":"CR-P","1768":"CR-P","1769":"CR-P","1773":"CR-P","1314":"CU-03","1478":"CU-08","1470":"CU-12","1709":"CU-14","1469":"CU-06","1468":"CU-04","1472":"CU-12","1315":"CU-01","1479":"CU-07","1471":"CU-09","1711":"CU-11","1476":"CU-08","1313":"CU-01","1464":"CU-04","1473":"CU-10","1463":"CU-04","1316":"CU-01","1480":"CU-09","1710":"CU-13","1467":"CU-04","1462":"CU-07","1445":"CU-01","1461":"CU-09","1474":"CU-12","1475":"CU-13","1724":"DO-32","1700":"DO-18","1729":"DO-14","1720":"DO-11","1723":"DO-01","1730":"DO-30","1722":"DO-04","1725":"DO-04","1721":"DO-17","1759":"DO-10","1702":"HT-ND","1699":"DO-15","1756":"DO-16","1717":"DO-11","1718":"PR-AL","1760":"HT-SD","1755":"HT-SD","1757":"HT-SD","1758":"HT-AR","1763":"HT-SD","1701":"HT-ND","1762":"JM-02","1482":"JM-08","1764":"JM-04","1761":"JM-04","1481":"JM-10","1483":"JM-09","1786":"MX-CHP","1440":"MX-YUC","1499":"MX-SON","1682":"MX-JAL","1526":"MX-SIN","1633":"MX-SON","1795":"MX-PUE","1518":"MX-BCS","1527":"MX-NAY","1525":"MX-NAY","1694":"MX-OAX","1693":"MX-GRO","1691":"MX-MOR","1680":"MX-GRO","1679":"MX-GRO","1688":"MX-GRO","1791":"MX-OAX","1442":"MX-YUC","1670":"MX-DIF","1780":"MX-CHP","1449":"MX-ROO","1436":"MX-ROO","1498":"MX-SON","1654":"MX-GUA","1669":"MX-PUE","1511":"MX-CHH","1514":"MX-CHH","1553":"MX-BCS","1632":"MX-SON","1646":"MX-CHH","1512":"MX-CHH","1532":"MX-BCN","1438":"MX-YUC","1681":"MX-COL","1458":"MX-YUC","1649":"MX-COL","1547":"MX-SON","1523":"MX-BCS","1443":"MX-ROO","1439":"MX-ROO","1582":"MX-COA","1686":"MX-JAL","1502":"MX-BCS","1552":"MX-BCS","1539":"MX-BCN","1541":"MX-SON","1662":"MX-JAL","1790":"MX-OAX","1460":"MX-CAM","1784":"MX-CAM","1778":"MX-OAX","1522":"MX-BCS","1792":"MX-OAX","1437":"MX-YUC","1779":"MX-TAB","1503":"MX-SIN","1775":"MX-CHP","1521":"MX-BCS","1312":"MX-ROO","1508":"MX-DUR","1777":"MX-OAX","1444":"MX-ROO","1528":"MX-BCN","1684":"MX-JAL","1782":"MX-CHP","1675":"MX-TAM","1671":"MX-VER","1788":"MX-CHP","1676":"MX-QUE","1794":"MX-VER","1672":"MX-TAM","1456":"MX-TAM","1584":"MX-NLE","1783":"MX-TAB","1529":"MX-BCN","1793":"MX-VER","1651":"MX-MIC","1504":"MX-DUR","1534":"MX-SON","1678":"MX-SLP","1683":"MX-JAL","1450":"MX-CAM","1787":"MX-CHP","1774":"MX-CHP","1781":"MX-CHP","1658":"MX-AGU","1789":"MX-OAX","1507":"MX-DUR","1656":"MX-MIC","1495":"MX-BCS","1653":"MX-QUE","1665":"MX-PUE","1661":"MX-ZAC","1447":"MX-CAM","1441":"MX-ROO","1540":"MX-SON","1095":"US-CA","1513":"MX-CHH","1664":"MX-AGU","1542":"US-CA","1597":"US-TX","1455":"MX-VER","1559":"MX-NLE","1587":"MX-NLE","1590":"US-TX","1568":"US-TX","1657":"MX-MEX","1776":"MX-OAX","1546":"MX-BCN","1505":"MX-DUR","1451":"MX-CHP","1667":"MX-VER","1524":"MX-NAY","1530":"MX-BCS","1535":"MX-BCN","1631":"US-NM","1448":"MX-CAM","1650":"MX-COL","1689":"MX-GRO","1500":"MX-SON","1555":"US-TX","1593":"MX-COA","1549":"MX-BCN","1668":"MX-VER","1545":"MX-BCN","1666":"MX-HID","1516":"MX-CHH","1785":"MX-TAB","1630":"MX-CHH","1544":"US-AZ","1550":"MX-BCS","1674":"MX-TAM","1457":"MX-TAM","1538":"MX-SON","1639":"US-AZ","1510":"MX-DUR","1606":"US-NM","1453":"MX-YUC","1652":"MX-MIC","1537":"MX-SON","1677":"MX-SLP","1629":"MX-SON","1551":"MX-BCS","1594":"MX-TAM","1599":"MX-NLE","1497":"MX-SON","1596":"US-TX","1496":"MX-SIN","1660":"MX-ZAC","1595":"US-TX","1493":"MX-SIN","1634":"MX-CHH","1673":"MX-SLP","1687":"MX-COL","1520":"MX-BCS","1492":"MX-SIN","1459":"MX-CAM","1446":"MX-ROO","1501":"MX-BCS","1506":"MX-DUR","1560":"MX-COA","1685":"MX-COL","1643":"MX-CHH","1604":"US-NM","1585":"MX-NLE","1589":"MX-COA","1648":"US-TX","1561":"US-TX","1491":"MX-SIN","1647":"MX-CHH","1628":"MX-SON","1591":"MX-DUR","1690":"MX-OAX","1543":"US-AZ","1517":"MX-DUR","1640":"US-AZ","1556":"US-TX","1598":"MX-TAM","1663":"MX-NAY","1583":"MX-COA","1519":"MX-BCS","1536":"MX-SON","1494":"MX-SIN","1641":"US-AZ","1586":"MX-ZAC","1554":"MX-BCS","1509":"MX-SIN","1454":"MX-YUC","1566":"US-TX","1659":"MX-ZAC","1655":"MX-MIC","1692":"MX-GRO","1515":"MX-CHH","1642":"MX-CHH","1567":"US-TX","1592":"MX-CHH","1588":"MX-CHH","1533":"US-CA","1548":"MX-BCS","1645":"US-TX","1741":"PA-8","1747":"PA-8","1744":"PA-2","1743":"PA-2","1748":"PA-1","1737":"PA-5","1740":"PA-5","1749":"PA-7","1746":"PA-9","1745":"PA-4","1765":"PA-3","1742":"PA-9","1739":"PA-8","1738":"PA-5","1716":"PR-CR","1719":"PR-AC","1728":"PR-SJ","1726":"PR-VQ","1727":"PR-CY","1712":"TC-","1695":"TC-","1713":"TC-","1703":"TC-","458":"CA-BC","1253":"CA-QC","1289":"CA-QC","1035":"US-WA","1275":"CA-ON","422":"CA-BC","1255":"CA-ON","1277":"CA-ON","1265":"CA-ON","1285":"CA-QC","461":"CA-BC","555":"CA-YT","1210":"CA-NS","1225":"CA-QC","1273":"CA-ON","1041":"CA-BC","1291":"CA-QC","1191":"CA-ON","1214":"CA-NB","339":"CA-AB","1276":"CA-ON","383":"CA-SK","459":"CA-BC","1223":"CA-QC","1212":"CA-NS","1278":"CA-ON","573":"CA-NL","445":"CA-AB","1218":"CA-NS","1230":"CA-NB","1192":"CA-ON","1217":"CA-NS","404":"CA-BC","1279":"CA-ON","481":"CA-AB","1047":"CA-BC","897":"CA-ON","336":"CA-BC","483":"CA-AB","895":"CA-ON","517":"CA-YT","456":"CA-AB","1215":"CA-NS","1045":"CA-BC","948":"CA-AB","455":"CA-AB","1287":"CA-QC","1231":"CA-NS","1267":"CA-ON","1221":"CA-QC","1193":"CA-ON","1252":"CA-QC","1247":"CA-QC","369":"CA-MB","1266":"CA-QC","1297":"CA-QC","1257":"CA-QC","1209":"CA-NB","1293":"CA-QC","586":"CA-NL","470":"CA-BC","447":"CA-BC","444":"CA-BC","932":"CA-SK","587":"CA-NL","577":"CA-NL","471":"CA-BC","1280":"CA-QC","568":"CA-NL","1248":"CA-QC","509":"CA-NT","463":"CA-BC","465":"CA-BC","374":"CA-AB","453":"CA-BC","372":"CA-AB","1240":"CA-NS","952":"CA-AB","1213":"CA-NS","1029":"US-WA","1269":"CA-ON","1254":"CA-ON","810":"CA-MB","464":"CA-BC","814":"CA-MB","1042":"CA-BC","1244":"CA-NS","886":"US-MI","412":"CA-BC","835":"CA-MB","901":"CA-ON","1270":"CA-QC","1224":"CA-NB","833":"CA-MB","408":"CA-BC","1046":"CA-BC","819":"CA-ON","1037":"CA-BC","1236":"CA-QC","451":"CA-AB","379":"CA-SK","485":"CA-AB","564":"CA-NL","366":"CA-SK","825":"CA-MB","1220":"US-ME","473":"CA-AB","891":"CA-ON","821":"CA-ON","1187":"CA-ON","845":"CA-ON","943":"CA-SK","822":"CA-MB","446":"CA-BC","1263":"US-VT","1249":"CA-QC","1189":"US-MI","479":"CA-AB","1211":"CA-NB","937":"CA-SK","1281":"CA-QC","263":"CA-ON","1036":"US-WA","946":"CA-SK","1044":"CA-BC","375":"CA-AB","1226":"US-ME","1219":"CA-QC","824":"CA-SK","405":"CA-BC","492":"CA-BC","371":"CA-AB","396":"CA-AB","522":"CA-YT","1290":"US-VT","347":"CA-NT","951":"CA-SK","474":"CA-AB","434":"CA-BC","212":"CA-QC","338":"CA-BC","460":"CA-BC","518":"CA-YT","1242":"CA-NS","820":"CA-ON","261":"CA-ON","484":"CA-AB","1227":"CA-NS","1245":"CA-QC","1274":"US-NY","1296":"CA-QC","566":"CA-NL","477":"CA-AB","894":"CA-ON","337":"CA-AB","811":"CA-MB","420":"CA-BC","419":"CA-BC","1043":"CA-BC","469":"CA-BC","565":"CA-NL","591":"CA-NL","508":"CA-NT","457":"CA-BC","373":"CA-AB","406":"CA-BC","274":"CA-ON","888":"CA-ON","397":"CA-AB","808":"CA-MB","168":"CA-NT","1272":"CA-ON","896":"US-MI","482":"CA-AB","341":"CA-BC","423":"CA-BC","823":"CA-MB","934":"CA-SK","480":"CA-AB","288":"CA-QC","286":"CA-QC","448":"CA-AB","1298":"CA-QC","826":"CA-MB","947":"CA-SK","936":"CA-SK","488":"CA-BC","216":"CA-QC","1268":"CA-ON","262":"CA-ON","486":"CA-BC","329":"CA-AB","809":"CA-ON","462":"CA-BC","524":"CA-BC","417":"CA-BC","427":"CA-BC","378":"CA-SK","381":"CA-SK","399":"CA-AB","554":"CA-YT","902":"CA-ON","933":"CA-SK","435":"CA-BC","1246":"CA-QC","557":"CA-YT","475":"CA-AB","367":"CA-SK","1234":"CA-NS","1232":"US-ME","938":"CA-SK","530":"US-AK","1238":"CA-NL","944":"US-ND","154":"CA-YT","149":"CA-YT","908":"CA-SK","440":"CA-BC","276":"CA-ON","254":"CA-ON","950":"CA-SK","1258":"CA-QC","1299":"CA-QC","834":"US-MN","567":"CA-NL","275":"CA-ON","232":"CA-MB","1256":"CA-QC","589":"CA-NL","452":"CA-AB","433":"CA-BC","487":"CA-AB","585":"CA-NL","360":"CA-SK","358":"CA-SK","478":"CA-AB","828":"CA-SK","884":"CA-ON","538":"CA-BC","853":"CA-MB","949":"CA-SK","844":"CA-ON","330":"CA-AB","365":"CA-MB","1235":"CA-QC","847":"CA-ON","843":"CA-ON","935":"CA-SK","556":"CA-YT","553":"CA-YT","491":"CA-AB","350":"CA-NT","328":"CA-AB","384":"CA-AB","220":"CA-QC","574":"CA-NL","1237":"CA-NL","476":"CA-AB","333":"CA-BC","1179":"US-NY","224":"CA-QC","432":"CA-BC","8":"CA-NU","289":"CA-QC","281":"CA-QC","889":"CA-ON","815":"CA-ON","489":"CA-BC","209":"CA-NL","299":"CA-NU","214":"CA-QC","400":"CA-BC","1271":"CA-QC","177":"CA-YT","472":"CA-AB","324":"CA-AB","505":"CA-NT","504":"CA-NT","529":"US-AK","6":"CA-NU","382":"CA-SK","421":"CA-BC","92":"US-AK","335":"CA-BC","297":"CA-NU","588":"CA-NL","855":"CA-MB","393":"CA-MB","391":"CA-MB","380":"CA-SK","449":"CA-AB","827":"CA-MB","512":"CA-NT","285":"CA-QC","290":"CA-QC","499":"CA-NU","331":"CA-BC","528":"CA-YT","885":"CA-ON","454":"US-MT","204":"CA-NU","306":"CA-QC","1251":"CA-QC","426":"US-AK","536":"CA-BC","525":"CA-BC","17":"CA-NT","1032":"CA-BC","533":"CA-YT","1283":"CA-QC","416":"CA-BC","414":"CA-BC","23":"CA-NU","1286":"CA-QC","223":"CA-QC","841":"CA-MB","225":"CA-QC","342":"CA-NT","526":"CA-YT","176":"CA-NT","170":"CA-NT","532":"CA-YT","1":"CA-NU","35":"CA-NU","21":"CA-NU","570":"CA-NL","10":"CA-NU","851":"CA-MB","264":"CA-ON","377":"CA-AB","1292":"US-ME","201":"CA-QC","334":"CA-BC","411":"CA-BC","401":"CA-BC","249":"CA-NU","592":"CA-NL","575":"CA-NL","340":"CA-AB","325":"CA-AB","323":"CA-AB","1295":"CA-QC","314":"CA-NU","1243":"CA-NS","1284":"CA-QC","312":"CA-NU","903":"CA-ON","410":"CA-BC","552":"CA-YT","287":"CA-ON","430":"CA-BC","813":"CA-ON","812":"CA-ON","309":"CA-NL","501":"CA-NU","30":"CA-NU","15":"CA-NU","7":"CA-NU","11":"CA-NU","9":"CA-NU","215":"CA-QC","210":"CA-QC","356":"CA-NT","2":"CA-NU","543":"CA-YT","174":"CA-YT","945":"US-ND","519":"CA-YT","279":"CA-ON","546":"CA-YT","544":"CA-YT","175":"CA-YT","172":"CA-YT","364":"CA-SK","521":"CA-YT","363":"CA-SK","302":"CA-NU","579":"CA-QC","581":"CA-QC","503":"CA-NT","496":"CA-NT","594":"CA-NL","520":"CA-YT","150":"CA-YT","439":"CA-BC","171":"CA-YT","13":"CA-NU","4":"CA-NU","203":"CA-NU","523":"CA-BC","246":"CA-MB","563":"CA-NL","14":"CA-NU","189":"CA-QC","198":"CA-QC","199":"CA-QC","188":"CA-QC","202":"CA-QC","190":"CA-QC","196":"CA-QC","197":"CA-QC","200":"CA-QC","307":"CA-QC","527":"CA-YT","413":"CA-BC","258":"CA-NU","450":"CA-BC","153":"CA-YT","293":"CA-ON","424":"CA-BC","260":"CA-ON","409":"CA-BC","539":"CA-BC","351":"CA-NT","349":"CA-NT","407":"CA-BC","346":"CA-NT","348":"CA-AB","1241":"CA-NS","310":"CA-NU","31":"CA-NU","547":"CA-YT","550":"CA-YT","370":"CA-SK","296":"CA-NU","313":"CA-NU","245":"CA-MB","211":"CA-QC","355":"CA-NT","183":"CA-YT","571":"CA-NL","438":"US-AK","1294":"CA-QC","549":"CA-YT","354":"CA-NT","344":"CA-NT","899":"US-MN","846":"CA-ON","345":"CA-NT","887":"CA-ON","311":"CA-NU","922":"US-MT","266":"CA-ON","359":"CA-SK","361":"CA-SK","244":"CA-MB","343":"CA-NT","265":"CA-ON","551":"CA-YT","317":"CA-NU","513":"CA-NT","580":"CA-QC","1250":"CA-QC","1239":"CA-QC","510":"CA-NT","590":"CA-NL","436":"CA-BC","230":"CA-NL","25":"CA-NU","295":"CA-ON","490":"CA-BC","402":"CA-BC","403":"CA-BC","269":"CA-ON","305":"CA-NU","1282":"CA-QC","291":"CA-NU","582":"CA-NL","303":"CA-NL","595":"CA-NL","593":"CA-NL","848":"CA-ON","569":"CA-NL","27":"CA-NT","389":"CA-SK","388":"CA-SK","229":"CA-NL","362":"CA-SK","167":"CA-YT","425":"CA-BC","250":"CA-NU","376":"CA-AB","233":"CA-MB","498":"CA-NU","500":"CA-NU","29":"CA-NU","516":"CA-NT","213":"CA-QC","386":"CA-SK","1133":"CA-NS","576":"CA-NL","842":"CA-ON","151":"US-AK","385":"CA-SK","507":"CA-SK","387":"CA-SK","219":"CA-QC","206":"CA-QC","243":"CA-MB","545":"CA-YT","5":"CA-NU","34":"CA-NU","320":"CA-NU","22":"CA-NU","368":"CA-SK","173":"CA-YT","1233":"CA-QC","418":"CA-BC","304":"CA-NU","497":"CA-NT","548":"CA-NT","542":"CA-YT","193":"CA-QC","148":"CA-YT","227":"CA-QC","326":"CA-AB","493":"CA-NT","146":"US-AK","235":"CA-MB","195":"CA-QC","3":"CA-NU","319":"CA-NU","327":"CA-AB","1030":"US-WA","272":"CA-ON","308":"CA-QC","248":"CA-MB","506":"CA-NU","431":"CA-BC","221":"CA-QC","267":"CA-ON","12":"CA-NU","277":"CA-ON","253":"CA-ON","255":"CA-ON","494":"CA-NT","208":"CA-QC","205":"CA-QC","234":"CA-MB","395":"CA-SK","1261":"US-NY","1033":"CA-BC","357":"CA-NT","392":"CA-SK","332":"CA-BC","850":"CA-MB","278":"CA-ON","511":"CA-SK","1216":"CA-NS","301":"CA-NU","24":"CA-NU","268":"CA-ON","1131":"US-MA","239":"CA-MB","849":"CA-MB","415":"CA-BC","390":"CA-MB","910":"US-MT","541":"CA-YT","284":"CA-QC","191":"CA-QC","228":"CA-QC","226":"CA-QC","155":"US-AK","273":"CA-ON","398":"CA-SK","535":"US-AK","152":"CA-YT","283":"CA-NU","316":"CA-NU","256":"CA-ON","502":"CA-NT","890":"US-MI","584":"CA-QC","270":"CA-ON","169":"CA-YT","839":"CA-ON","298":"CA-NU","300":"CA-NU","429":"CA-BC","838":"CA-ON","280":"CA-QC","26":"CA-NU","322":"CA-NU","192":"CA-NU","28":"CA-NU","428":"CA-BC","852":"CA-MB","578":"CA-QC","583":"CA-QC","840":"CA-ON","271":"CA-ON","236":"CA-ON","237":"CA-ON","572":"CA-NL","37":"CA-NU","18":"CA-NU","19":"CA-NU","836":"CA-ON","32":"CA-NU","33":"CA-NU","20":"CA-NU","0":"CA-NU","240":"CA-MB","321":"CA-NU","292":"CA-ON","318":"CA-NU","495":"CA-NT","294":"CA-ON","238":"CA-ON","252":"CA-NU","179":"US-AK","394":"CA-MB","218":"CA-QC","442":"US-AK","352":"CA-NT","514":"CA-NU","217":"CA-QC","282":"CA-ON","257":"CA-ON","194":"CA-QC","837":"CA-ON","231":"CA-QC","222":"CA-QC","207":"CA-QC","259":"CA-ON","97":"US-AK","242":"CA-MB","16":"CA-NU","534":"US-AK","353":"CA-YT","315":"CA-NU","515":"CA-NU","251":"CA-MB","241":"CA-MB","36":"CA-NU","854":"CA-MB","247":"CA-MB","1137":"US-MA","972":"US-CA","1138":"US-MA","1190":"US-OH","1156":"US-VA","1184":"US-PA","1577":"US-TX","1015":"US-OR","1055":"US-OR","882":"US-WI","1075":"US-CA","101":"US-AK","1074":"US-CA","1575":"US-TX","978":"US-CA","1010":"US-ID","1136":"US-MA","1139":"US-MA","1124":"US-NY","1161":"US-IN","769":"US-TX","864":"US-MI","1611":"US-AZ","974":"US-CA","1185":"US-NJ","792":"US-KS","1635":"US-AZ","1180":"US-MD","1034":"US-WA","673":"US-TN","1140":"US-ME","683":"US-TN","1181":"US-MD","1142":"US-NH","1039":"US-WA","672":"US-TN","1160":"US-OH","1621":"US-NM","1564":"US-TX","1099":"US-CA","730":"US-UT","1337":"US-FL","1208":"US-VA","1374":"US-FL","1120":"US-PA","1159":"US-OH","1027":"US-UT","971":"US-OR","1000":"US-MT","670":"US-TN","1096":"US-CA","756":"US-WY","879":"US-WI","1402":"US-SC","878":"US-IL","1489":"US-HI","721":"US-CO","976":"US-CA","696":"US-KY","1052":"US-WA","1091":"US-CA","1395":"US-TN","1118":"US-NY","1040":"US-WA","1087":"US-NV","1614":"US-NM","711":"US-CO","1164":"US-OH","1038":"US-WA","923":"US-MT","1401":"US-SC","880":"US-IL","661":"US-MO","1574":"US-TX","958":"US-CA","1353":"US-TX","720":"US-CO","1354":"US-TX","468":"US-WA","877":"US-WI","1102":"US-CA","1146":"US-VA","726":"US-UT","997":"US-ID","987":"US-WA","1100":"US-CA","1288":"US-ME","1260":"US-NY","80":"US-AK","1323":"US-LA","540":"US-AK","1200":"US-NC","1105":"US-AZ","747":"US-CO","1264":"US-VT","1612":"US-AZ","928":"US-WY","1397":"US-TN","1332":"US-MS","437":"US-AK","648":"US-IA","644":"US-MN","1186":"US-PA","1101":"US-CA","766":"US-TX","960":"US-CA","713":"US-CO","736":"US-CO","925":"US-MT","1400":"US-GA","1198":"US-SC","758":"US-WY","703":"US-IA","693":"US-IL","1352":"US-TX","700":"US-IN","861":"US-MI","651":"US-MN","1016":"US-OR","1092":"US-CA","1071":"US-NV","984":"US-ID","1205":"US-NC","1098":"US-CA","961":"US-OR","1149":"US-PA","710":"US-CO","1626":"US-NM","620":"US-MO","1031":"US-WA","914":"US-SD","1172":"US-OH","467":"US-WA","1158":"US-VA","860":"US-MI","1122":"US-CT","1051":"US-OR","991":"US-OR","1624":"US-NM","1020":"US-OR","1304":"US-FL","1557":"US-TX","778":"US-TX","1176":"US-PA","1196":"US-NC","800":"US-OK","83":"US-AK","1163":"US-OH","717":"US-CO","680":"US-MO","1097":"US-CA","1117":"US-MA","707":"US-IA","1019":"US-OR","954":"US-CA","1558":"US-TX","621":"US-NE","1576":"US-TX","1580":"US-TX","1563":"US-TX","1228":"US-ME","1413":"US-SC","1434":"US-FL","1351":"US-TX","667":"US-MO","883":"US-WI","857":"US-MI","88":"US-AK","1328":"US-LA","45":"US-AK","1392":"US-GA","645":"US-MN","962":"US-CA","868":"US-MI","859":"US-WI","1050":"US-OR","1396":"US-TN","617":"US-MN","760":"US-OK","1024":"US-ID","975":"US-CA","689":"US-IL","1613":"US-AZ","1123":"US-NY","999":"US-WY","441":"US-AK","1429":"US-FL","759":"US-OK","1170":"US-WV","1570":"US-TX","1262":"US-NY","1183":"US-VA","134":"US-AK","1618":"US-NM","1162":"US-OH","695":"US-IL","731":"US-CO","979":"US-ID","1068":"US-CA","863":"US-MI","1093":"US-CA","1408":"US-NC","1107":"US-AZ","98":"US-AK","643":"US-MN","1177":"US-NY","893":"US-MI","1081":"US-AZ","1637":"US-AZ","1111":"US-AZ","1307":"US-FL","871":"US-WI","685":"US-AR","986":"US-WA","1054":"US-OR","691":"US-IL","872":"US-MN","955":"US-CA","1104":"US-CA","767":"US-TX","1638":"US-AZ","1188":"US-OH","1433":"US-FL","1336":"US-MS","1259":"US-NY","531":"US-AK","128":"US-AK","1303":"US-FL","1372":"US-FL","1377":"US-FL","1154":"US-VA","1311":"US-FL","1194":"US-NC","1201":"US-NC","1197":"US-NC","1153":"US-NC","671":"US-MS","1398":"US-GA","1057":"US-CA","1106":"US-AZ","1627":"US-NM","1376":"US-FL","1327":"US-AR","990":"US-OR","789":"US-KS","1178":"US-PA","762":"US-OK","1569":"US-TX","1388":"US-GA","881":"US-WI","724":"US-UT","715":"US-CO","749":"US-NE","963":"US-CA","1432":"US-GA","1331":"US-AL","965":"US-OR","750":"US-NE","1058":"US-CA","790":"US-KS","1403":"US-SC","1061":"US-CA","1394":"US-TN","699":"US-KY","799":"US-AR","1605":"US-AZ","1182":"US-VA","1404":"US-SC","1329":"US-TX","892":"US-MI","969":"US-CA","677":"US-KS","1078":"US-UT","970":"US-OR","782":"US-TX","1616":"US-TX","1309":"US-FL","1581":"US-TX","1121":"US-NJ","1409":"US-NC","1155":"US-NC","662":"US-IL","690":"US-IN","1175":"US-PA","1317":"US-LA","992":"US-OR","1389":"US-SC","867":"US-MI","684":"US-AR","795":"US-AR","735":"US-CO","1349":"US-TX","722":"US-CO","1318":"US-LA","1359":"US-LA","1308":"US-FL","466":"US-ID","1056":"US-OR","674":"US-TN","706":"US-MO","104":"US-AK","678":"US-MO","676":"US-MO","74":"US-AK","995":"US-MT","763":"US-OK","1406":"US-SC","1414":"US-SC","719":"US-CO","718":"US-CO","1608":"US-AZ","818":"US-MN","1069":"US-NV","977":"US-CA","788":"US-KS","1572":"US-TX","1150":"US-MD","1127":"US-MD","1006":"US-MT","1202":"US-NC","931":"US-MT","1082":"US-UT","162":"US-AK","1018":"US-OR","1420":"US-FL","1421":"US-FL","1435":"US-FL","646":"US-ND","1378":"US-FL","1399":"US-TN","989":"US-WA","1373":"US-FL","1305":"US-FL","1330":"US-LA","1487":"US-HI","1419":"US-FL","1415":"US-FL","1110":"US-CA","1067":"US-NV","803":"US-CO","996":"US-MT","1306":"US-FL","862":"US-MI","732":"US-CO","1603":"US-NM","70":"US-AK","1174":"US-PA","121":"US-AK","1204":"US-NC","1578":"US-TX","1077":"US-UT","1147":"US-OH","874":"US-WI","647":"US-MN","830":"US-MN","988":"US-ID","709":"US-IA","875":"US-WI","1108":"US-AZ","1355":"US-TX","1644":"US-TX","993":"US-MT","761":"US-OK","1571":"US-TX","957":"US-CA","1619":"US-NM","166":"US-AK","159":"US-AK","1325":"US-OK","1053":"US-WA","959":"US-CA","918":"US-MT","1168":"US-KY","140":"US-AK","1195":"US-NC","641":"US-MN","1488":"US-HI","1731":"US-HI","1173":"US-PA","743":"US-SD","1410":"US-NC","921":"US-MT","939":"US-ND","77":"US-AK","1059":"US-CA","858":"US-WI","1333":"US-FL","727":"US-UT","127":"US-AK","973":"US-CA","1203":"US-NC","106":"US-AK","1735":"US-HI","786":"US-TX","1022":"US-ID","742":"US-WY","443":"US-AK","1094":"US-CA","1103":"US-CA","656":"US-SD","729":"US-UT","1343":"US-MS","1418":"US-GA","1014":"US-OR","980":"US-OR","777":"US-KS","1623":"US-NM","1151":"US-OH","1145":"US-WV","609":"US-AK","1579":"US-TX","1322":"US-LA","1342":"US-MS","776":"US-NM","964":"US-CA","632":"US-SD","1423":"US-AL","1427":"US-AL","1070":"US-NV","1734":"US-HI","737":"US-UT","1222":"US-ME","697":"US-KY","865":"US-MI","1417":"US-FL","1411":"US-NC","653":"US-MN","44":"US-AK","1602":"US-NM","768":"US-TX","1736":"US-HI","866":"US-IN","1390":"US-GA","1002":"US-MT","668":"US-TN","623":"US-IA","1486":"US-HI","1600":"US-NM","1341":"US-MS","1171":"US-WV","1609":"US-NM","1003":"US-MT","911":"US-ND","1021":"US-ID","966":"US-OR","927":"US-WY","1199":"US-NC","681":"US-MO","628":"US-NE","622":"US-MO","968":"US-OR","983":"US-ID","616":"US-SD","953":"US-CA","926":"US-WY","136":"US-AK","745":"US-CO","1428":"US-AL","1622":"US-NM","734":"US-NM","1636":"US-AZ","1165":"US-IN","1601":"US-NM","625":"US-NE","1083":"US-AZ","716":"US-WY","1430":"US-GA","1625":"US-NM","967":"US-OR","649":"US-IA","1004":"US-MT","764":"US-OK","723":"US-CO","794":"US-OK","770":"US-OK","765":"US-OK","771":"US-TX","1157":"US-VA","797":"US-OK","669":"US-AL","796":"US-OK","605":"US-AK","869":"US-MI","619":"US-NE","801":"US-KS","1387":"US-GA","876":"US-MN","748":"US-CO","1338":"US-MS","751":"US-WY","915":"US-ND","652":"US-MN","688":"US-AR","856":"US-WI","1167":"US-VA","1080":"US-UT","772":"US-OK","744":"US-WY","738":"US-WY","913":"US-MT","1347":"US-LA","650":"US-IA","701":"US-KY","1424":"US-GA","102":"US-AK","666":"US-IL","1229":"US-ME","1615":"US-NM","775":"US-NM","1620":"US-NM","66":"US-AK","698":"US-IN","733":"US-UT","1416":"US-AL","832":"US-ND","1617":"US-NM","781":"US-TX","607":"US-AK","1426":"US-AL","702":"US-IN","692":"US-IL","694":"US-IN","1005":"US-ID","754":"US-WY","985":"US-ID","72":"US-AK","714":"US-WY","99":"US-AK","657":"US-SD","640":"US-MN","1017":"US-OR","816":"US-MN","1011":"US-NV","1079":"US-UT","1076":"US-NV","627":"US-NE","1393":"US-GA","752":"US-WY","598":"US-AK","831":"US-ND","904":"US-MT","184":"US-AK","1206":"US-VA","1152":"US-VA","873":"US-WI","642":"US-SD","829":"US-ND","940":"US-ND","900":"US-MI","663":"US-MO","139":"US-AK","665":"US-IL","1013":"US-NV","1009":"US-ID","1026":"US-ID","1085":"US-NV","1088":"US-NV","1084":"US-NV","1090":"US-NV","929":"US-MT","1064":"US-CA","1065":"US-NV","708":"US-IL","774":"US-TX","658":"US-ND","942":"US-ND","982":"US-ID","1169":"US-TN","704":"US-IL","806":"US-KS","804":"US-KS","755":"US-WY","1610":"US-AZ","69":"US-AK","62":"US-AK","558":"US-AK","612":"US-SD","1607":"US-AZ","705":"US-MO","1412":"US-SC","687":"US-AR","1391":"US-GA","124":"US-AK","87":"US-AK","122":"US-AK","635":"US-NE","624":"US-IA","664":"US-MO","1340":"US-MS","81":"US-AK","1063":"US-NV","1008":"US-OR","1565":"US-TX","1339":"US-AR","712":"US-CO","783":"US-TX","1326":"US-AR","1001":"US-ID","1350":"US-TX","613":"US-IA","1028":"US-WA","1109":"US-AZ","633":"US-NE","920":"US-MT","1422":"US-AL","1562":"US-TX","870":"US-WI","1324":"US-AR","631":"US-SD","636":"US-NE","1049":"US-OR","1148":"US-WV","798":"US-MO","1207":"US-NC","606":"US-AK","638":"US-NE","787":"US-KS","675":"US-MO","1425":"US-AL","634":"US-NE","178":"US-AK","56":"US-AK","791":"US-KS","924":"US-MT","919":"US-MT","1334":"US-AL","807":"US-CO","1732":"US-HI","785":"US-TX","65":"US-AK","740":"US-WY","779":"US-NM","164":"US-AK","165":"US-AK","1089":"US-NV","898":"US-MI","1344":"US-MS","108":"US-AK","596":"US-AK","157":"US-AK","1321":"US-LA","780":"US-TX","91":"US-AK","130":"US-AK","626":"US-SD","941":"US-ND","905":"US-MT","602":"US-AK","1025":"US-UT","615":"US-NE","1073":"US-NV","686":"US-MO","739":"US-NE","614":"US-SD","679":"US-MO","773":"US-TX","1320":"US-MS","1129":"US-NY","682":"US-AR","994":"US-MT","728":"US-UT","1023":"US-ID","805":"US-KS","1319":"US-LA","746":"US-CO","909":"US-MT","1358":"US-LA","73":"US-AK","118":"US-AK","119":"US-AK","94":"US-AK","115":"US-AK","112":"US-AK","802":"US-KS","817":"US-MN","111":"US-AK","1007":"US-NV","655":"US-SD","1012":"US-NV","105":"US-AK","123":"US-AK","793":"US-KS","93":"US-AK","1166":"US-KY","1066":"US-NV","916":"US-ND","599":"US-AK","659":"US-ND","185":"US-AK","1357":"US-LA","559":"US-AK","741":"US-WY","917":"US-MT","95":"US-AK","784":"US-TX","181":"US-AK","57":"US-AK","654":"US-SD","639":"US-NE","537":"US-AK","113":"US-AK","55":"US-AK","1119":"US-NY","1132":"US-MA","1112":"US-MA","186":"US-AK","1490":"US-HI","76":"US-AK","133":"US-AK","51":"US-AK","1086":"US-UT","1115":"US-MA","90":"US-AK","46":"US-AK","660":"US-ND","54":"US-AK","981":"US-ID","63":"US-AK","161":"US-AK","68":"US-AK","1361":"US-LA","158":"US-AK","1484":"US-HI","1048":"US-OR","52":"US-AK","757":"US-WY","753":"US-WY","906":"US-MT","160":"US-AK","86":"US-AK","103":"US-AK","1072":"US-NV","60":"US-AK","163":"US-AK","182":"US-AK","114":"US-AK","129":"US-AK","89":"US-AK","125":"US-AK","1405":"US-GA","930":"US-MT","1141":"US-ME","562":"US-AK","42":"US-AK","49":"US-AK","43":"US-AK","998":"US-ID","725":"US-UT","39":"US-AK","41":"US-AK","1366":"US-GA","96":"US-AK","141":"US-AK","109":"US-AK","126":"US-AK","135":"US-AK","180":"US-AK","630":"US-SD","637":"US-NE","117":"US-AK","604":"US-AK","618":"US-SD","64":"US-AK","110":"US-AK","1573":"US-TX","50":"US-AK","1116":"US-MA","629":"US-NE","116":"US-AK","601":"US-AK","82":"US-AK","85":"US-AK","84":"US-AK","71":"US-AK","1062":"US-CA","1060":"US-CA","560":"US-AK","61":"US-AK","600":"US-AK","79":"US-AK","603":"US-AK","561":"US-AK","1125":"US-MD","78":"US-AK","907":"US-MT","145":"US-AK","1113":"US-NY","1407":"US-SC","1310":"US-FL","1300":"US-FL","608":"US-AK","1130":"US-NJ","156":"US-AK","107":"US-AK","1431":"US-FL","1302":"US-FL","1375":"US-FL","48":"US-AK","611":"US-AK","1348":"US-TX","912":"US-SD","1114":"US-MA","1360":"US-LA","100":"US-AK","187":"US-AK","147":"US-AK","1346":"US-TX","120":"US-AK","597":"US-AK","1128":"US-MD","75":"US-AK","1301":"US-FL","1356":"US-LA","1335":"US-LA","143":"US-AK","138":"US-AK","40":"US-AK","1733":"US-HI","47":"US-AK","132":"US-AK","144":"US-AK","1452":"US-TX","59":"US-AK","38":"US-AK","131":"US-AK","956":"US-CA","142":"US-AK","137":"US-AK","67":"US-AK","1485":"US-HI","610":"US-AK","53":"US-AK","1126":"US-MD","58":"US-AK","1345":"US-LA","1367":"US-FL","1134":"US-MA","1531":"US-CA","1135":"US-MA"}